Metadata-Version: 2.1
Name: debug-dnnn
Version: 0.0.1
Summary: PyPI Tutorial
Home-page: https://github.com/
Author: liheyou
Author-email: author@example.com
License: UNKNOWN
Platform: UNKNOWN
Classifier: Programming Language :: Python :: 3
Classifier: License :: OSI Approved :: MIT License
Classifier: Operating System :: OS Independent
